filesig/filesig.py
filesig-0.3.data/scripts/filesig.py
filesig-0.3.dist-info/METADATA
filesig-0.3.dist-info/RECORD
filesig-0.3.dist-info/WHEEL
filesig-0.3.dist-info/top_level.txt
