Metadata-Version: 2.1
Name: filesig
Version: 0.3
Summary: Python command on top of 'poppler-utils' and 'openssl' used to verify file signatures
Home-page: https://github.com/peppelinux/FileSignatureValidator
Author: Giuseppe De Marco
Author-email: giuseppe.demarco@unical.it
License: BSD
Platform: UNKNOWN
Classifier: Development Status :: 5 - Production/Stable
Classifier: License :: OSI Approved :: BSD License
Classifier: Programming Language :: Python :: 2
Classifier: Programming Language :: Python :: 3
